{
  "CurrentAccount": "521243010531",
  "FargateContainerSecurityGroup": "sg-0940d8eebc22f52b1",
  "ECSTaskRole": "arn:aws:iam::521243010531:role/mrw-ECSTaskRole-KS4Z1KQTQX42",
  "PrivateSubnetTwo": "subnet-0de5827fbdbed0b28",
  "CurrentRegion": "us-west-2",
  "VPCId": "vpc-0486c569c3d588d3f",
  "CodeBuildRole": "arn:aws:iam::521243010531:role/MythicalMysfitsServiceCodeBuildServiceRole",
  "CodePipelineRole": "arn:aws:iam::521243010531:role/MythicalMysfitsServiceCodePipelineServiceRole",
  "DynamoTable": "Table-mrw",
  "EcsServiceRole": "arn:aws:iam::521243010531:role/mrw-EcsServiceRole-Y2AGLLUZAQ2G",
  "PrivateSubnetOne": "subnet-06af1fc4f054a628b",
  "PublicSubnetOne": "subnet-0314e3706afabcbf4",
  "PublicSubnetTwo": "subnet-0d4f090c628ea8f82"
}
